{
  "core": {
    "vtwonenCore": {
      "color": {
        "saffronMango": {
          "100": {
            "value": "#fefaef",
            "type": "color"
          },
          "200": {
            "value": "#fdeecd",
            "type": "color"
          },
          "300": {
            "value": "#fce6b4",
            "type": "color"
          },
          "400": {
            "value": "#fada92",
            "type": "color"
          },
          "500": {
            "value": "#f9d37d",
            "type": "color"
          },
          "600": {
            "value": "#f8c85d",
            "type": "color"
          },
          "700": {
            "value": "#e2b655",
            "type": "color"
          },
          "800": {
            "value": "#b08e42",
            "type": "color"
          },
          "900": {
            "value": "#886e33",
            "type": "color"
          },
          "1000": {
            "value": "#685427",
            "type": "color"
          }
        },
        "redRibbon": {
          "100": {
            "value": "#fce6ed",
            "type": "color"
          },
          "200": {
            "value": "#f7b0c6",
            "type": "color"
          },
          "300": {
            "value": "#f38aaa",
            "type": "color"
          },
          "400": {
            "value": "#ed5484",
            "type": "color"
          },
          "500": {
            "value": "#e9336c",
            "type": "color"
          },
          "600": {
            "value": "#e40047",
            "type": "color"
          },
          "700": {
            "value": "#cf0041",
            "type": "color"
          },
          "800": {
            "value": "#a20032",
            "type": "color"
          },
          "900": {
            "value": "#7d0027",
            "type": "color"
          },
          "1000": {
            "value": "#60001e",
            "type": "color"
          }
        },
        "background": {
          "1": {
            "value": "#ececec",
            "type": "color"
          },
          "2": {
            "value": "#c3c4c5",
            "type": "color"
          },
          "3": {
            "value": "#c7d2d8",
            "type": "color"
          },
          "4": {
            "value": "#ebf0f5",
            "type": "color"
          },
          "5": {
            "value": "#ebf5f1",
            "type": "color"
          },
          "6": {
            "value": "#c7d8d4",
            "type": "color"
          },
          "7": {
            "value": "#f2f5eb",
            "type": "color"
          },
          "8": {
            "value": "#d4d8c7",
            "type": "color"
          },
          "9": {
            "value": "#f5f2eb",
            "type": "color"
          },
          "10": {
            "value": "#d0cbb8",
            "type": "color"
          },
          "11": {
            "value": "#f5f0eb",
            "type": "color"
          },
          "12": {
            "value": "#d8d1c7",
            "type": "color"
          },
          "13": {
            "value": "#f4ebeb",
            "type": "color"
          },
          "14": {
            "value": "#d8c7c8",
            "type": "color"
          },
          "15": {
            "value": "#354D5C",
            "type": "color"
          },
          "16": {
            "value": "#685427",
            "type": "color"
          },
          "17": {
            "value": "#5B3537",
            "type": "color"
          },
          "18": {
            "value": "#4D5355",
            "type": "color"
          }
        }
      },
      "fontWeight": {
        "300": {
          "value": "Light",
          "type": "fontWeights"
        },
        "400": {
          "value": "Regular",
          "type": "fontWeights"
        },
        "500": {
          "value": "Medium",
          "type": "fontWeights"
        },
        "600": {
          "value": "Semibold",
          "type": "fontWeights"
        },
        "700": {
          "value": "Bold",
          "type": "fontWeights"
        }
      },
      "font": {
        "primary": {
          "value": "Proxima Nova",
          "type": "fontFamilies"
        },
        "accent": {
          "value": "Playfair Display",
          "type": "fontFamilies"
        }
      }
    }
  }
}